bootyprint/__init__.py
bootyprint/apps.py
bootyprint/models.py
bootyprint/settings.py
bootyprint/urls.py
bootyprint/utils.py
bootyprint/views.py
bootyprint/static/bootyprint/bootyprint.min.css
bootyprint/templates/bootyprint/default.html
bootyprint/templatetags/__init__.py
bootyprint/templatetags/bootyprint.py
django_bootyprint-0.0.5.dist-info/METADATA
django_bootyprint-0.0.5.dist-info/WHEEL
django_bootyprint-0.0.5.dist-info/licenses/LICENSE
django_bootyprint-0.0.5.dist-info/RECORD
