Metadata-Version: 2.4
Name: django-bootyprint
Version: 0.0.5
Summary: A Django app for rendering PDF documents with WeasyPrint
Project-URL: Homepage, https://github.com/SvenBroeckling/django-bootyprint
Project-URL: Bug Tracker, https://github.com/SvenBroeckling/django-bootyprint/issues
Author-email: Your Name <your.email@example.com>
License: MIT
License-File: LICENSE
Keywords: django,pdf,template,weasyprint
Classifier: Development Status :: 3 - Alpha
Classifier: Environment :: Web Environment
Classifier: Framework :: Django
Classifier: Framework :: Django :: 5.1
Classifier: Intended Audience :: Developers
Classifier: License :: OSI Approved :: MIT License
Classifier: Programming Language :: Python
Classifier: Programming Language :: Python :: 3
Classifier: Programming Language :: Python :: 3.13
Classifier: Topic :: Software Development :: Libraries :: Python Modules
Requires-Python: >=3.11
Requires-Dist: django>=5.1.7
Requires-Dist: weasyprint>=65.0
